safe_earth/__init__.py
safe_earth/data/__init__.py
safe_earth/data/climate/__init__.py
safe_earth/data/climate/era5.py
safe_earth/data/climate/wb2.py
safe_earth/data/climate/wb2_stores.py
safe_earth/data/strata/__init__.py
safe_earth/data/strata/gdf_territory_region_income.csv
safe_earth/data/strata/generate_gdf.py
safe_earth/data/strata/generate_landmasks.py
safe_earth/data/strata/territory_region_income.geojson
safe_earth/metrics/__init__.py
safe_earth/metrics/errors.py
safe_earth/metrics/fairness.py
safe_earth/metrics/losses.py
safe_earth/utils/__init__.py
safe_earth/utils/errors.py
safe_earth/utils/geometry_funcs.py
safe_earth/utils/stats.py
safe_earth/utils/surface_area.py
safe_earth/utils/xarray_funcs.py
safe_earth/viz/__init__.py
safe_earth/viz/viz_metrics.py
safe_earth-0.1.9.dist-info/METADATA
safe_earth-0.1.9.dist-info/WHEEL
safe_earth-0.1.9.dist-info/licenses/LICENSE
safe_earth-0.1.9.dist-info/RECORD
