Metadata-Version: 2.4
Name: safe-earth
Version: 0.1.9
Summary: Stratified Assessments of Forecasts over Earth
Project-URL: Repository, https://github.com/n-masi/safe
Project-URL: Homepage, https://n-masi.github.io/safe/
Author-email: Nick Masi <nicholas_masi@alumni.brown.edu>, Daniel Cai <daniel_cai@brown.edu>, Randall Balestriero <randall_balestriero@brown.edu>
License-Expression: MIT
License-File: LICENSE
Keywords: climate,earth,fairness,machine learning,stratification,weather
Requires-Dist: cfgrib
Requires-Dist: fsspec
Requires-Dist: gcsfs
Requires-Dist: geopandas
Requires-Dist: kaleido
Requires-Dist: numpy
Requires-Dist: pandas
Requires-Dist: plotly
Requires-Dist: pygeoboundaries-geolab
Requires-Dist: pytest
Requires-Dist: requests-cache
Requires-Dist: shapely
Requires-Dist: xarray
Requires-Dist: zarr
